climatempopy/__init__.py
climatempopy/climatempo.py
climatempopy/common.py
climatempopy/const.py
climatempopy-0.0.7.data/scripts/get_localeID
climatempopy-0.0.7.data/scripts/get_weather_by_localeID
climatempopy-0.0.7.data/scripts/get_weather_georeferenced
climatempopy-0.0.7.dist-info/LICENSE
climatempopy-0.0.7.dist-info/METADATA
climatempopy-0.0.7.dist-info/WHEEL
climatempopy-0.0.7.dist-info/top_level.txt
climatempopy-0.0.7.dist-info/RECORD
