Metadata-Version: 2.1
Name: climatempopy
Version: 0.0.7
Summary: A Clima Tempo API Python Wrapper
Home-page: https://github.com/tonyldo/climatempopy
Author: Antonio Campos
Author-email: tonyldo@gmail.com
License: UNKNOWN
Platform: UNKNOWN
Classifier: Programming Language :: Python :: 3
Classifier: License :: OSI Approved :: MIT License
Classifier: Operating System :: OS Independent
Requires-Python: >=3.6
Requires-Dist: aiohttp (==3.7.3)
Requires-Dist: geopy (==2.1.0)
Requires-Dist: pytest (==6.2.1)
Requires-Dist: pytest-asyncio (==0.14.0)
Requires-Dist: Unidecode (==1.1.2)
